.gitignore
.travis.yml
CHANGES.rst
MANIFEST.in
Makefile
README.rst
app.js
kitconcept.png
requirements.txt
setup.cfg
setup.py
WebpackLibrary/__init__.py
docs/index.html
robotframework_webpack.egg-info/PKG-INFO
robotframework_webpack.egg-info/SOURCES.txt
robotframework_webpack.egg-info/dependency_links.txt
robotframework_webpack.egg-info/entry_points.txt
robotframework_webpack.egg-info/not-zip-safe
robotframework_webpack.egg-info/requires.txt
robotframework_webpack.egg-info/top_level.txt