Metadata-Version: 1.1
Name: robotframework-webpack
Version: 1.1.1
Summary: A Robot Framework library for Webpack.
Home-page: https://kitconcept.com
Author: Timo Stollenwerk | kitconcept GmbH
Author-email: stollenwerk@kitconcept.com
License: Apache License 2.0
Keywords: robotframework webpack javascript react angular vue
Platform: UNKNOWN
Classifier: Development Status :: 5 - Production/Stable
Classifier: License :: OSI Approved :: Apache Software License
Classifier: Environment :: Web Environment
Classifier: Framework :: Robot Framework
Classifier: Framework :: Robot Framework :: Library
Classifier: Programming Language :: Python :: 2.7
Classifier: Programming Language :: Python :: 3.5
Classifier: Programming Language :: Python :: Implementation :: CPython
